bk_sales_stock/__init__.py
bk_sales_stock/bk_check_invoiced.py
bk_sales_stock/bk_main.py
bk_sales_stock/bk_prices.py
bk_sales_stock-0.1.8.dist-info/METADATA
bk_sales_stock-0.1.8.dist-info/WHEEL
bk_sales_stock-0.1.8.dist-info/entry_points.txt
bk_sales_stock-0.1.8.dist-info/top_level.txt
bk_sales_stock-0.1.8.dist-info/RECORD
